CHANGELOG.md
CITATION
LICENSE
MANIFEST.in
README.md
setup.py
gsee/__init__.py
gsee/_version.py
gsee/brl_model.py
gsee/pv.py
gsee/trigon.py
gsee.egg-info/PKG-INFO
gsee.egg-info/SOURCES.txt
gsee.egg-info/dependency_links.txt
gsee.egg-info/not-zip-safe
gsee.egg-info/requires.txt
gsee.egg-info/top_level.txt
gsee/climatedata_interface/__init__.py
gsee/climatedata_interface/generate_pdfs.py
gsee/climatedata_interface/interface.py
gsee/climatedata_interface/kt_h_sinusfunc.c
gsee/climatedata_interface/kt_h_sinusfunc.pyx
gsee/climatedata_interface/pre_gsee_processing.py
gsee/climatedata_interface/progress.py
gsee/climatedata_interface/util.py