Metadata-Version: 2.1
Name: gsee
Version: 0.3.0
Summary: GSEE: Global Solar Energy Estimator
Home-page: https://github.com/renewables-ninja/gsee
Author: Stefan Pfenninger
Author-email: stefan@pfenninger.org
License: UNKNOWN
Platform: UNKNOWN
Classifier: Development Status :: 4 - Beta
Classifier: Intended Audience :: Science/Research
Classifier: Programming Language :: Python
Classifier: Programming Language :: Python :: 3
Provides-Extra: generate_pdfs
